agent/__init__.py
agent/generator.py
agent/types.py
agent/a2a/__init__.py
agent/a2a/agentcard.py
agent/api/__init__.py
agent/api/app.py
agent/api/rate_limiting.py
agent/api/request_logging.py
agent/api/routes.py
agent/api/streaming.py
agent/capabilities/__init__.py
agent/capabilities/manager.py
agent/cli/__init__.py
agent/cli/__main__.py
agent/cli/cli_utils.py
agent/cli/main.py
agent/cli/style.py
agent/cli/commands/__init__.py
agent/cli/commands/deploy.py
agent/cli/commands/init.py
agent/cli/commands/init_agent.py
agent/cli/commands/plugin.py
agent/cli/commands/plugin_info.py
agent/cli/commands/plugin_init.py
agent/cli/commands/plugin_manage.py
agent/cli/commands/run.py
agent/cli/commands/validate.py
agent/config/__init__.py
agent/config/a2a.py
agent/config/constants.py
agent/config/intent.py
agent/config/logging.py
agent/config/model.py
agent/config/plugin_resolver.py
agent/config/settings.py
agent/config/yaml_source.py
agent/core/__init__.py
agent/core/base.py
agent/core/dispatcher.py
agent/core/executor.py
agent/core/function_executor.py
agent/core/memory_integration.py
agent/core/model.py
agent/core/models/__init__.py
agent/core/models/configuration.py
agent/core/models/iteration.py
agent/core/models/memory.py
agent/core/strategies/__init__.py
agent/core/strategies/iterative.py
agent/core/strategies/reactive.py
agent/integrations/README.md
agent/integrations/__init__.py
agent/integrations/config.py
agent/integrations/crewai/__init__.py
agent/integrations/crewai/a2a_client.py
agent/integrations/crewai/agentup_tool.py
agent/integrations/crewai/discovery.py
agent/integrations/crewai/models.py
agent/integrations/examples/__init__.py
agent/integrations/examples/basic_crew.py
agent/integrations/examples/multi_agent_flow.py
agent/integrations/examples/streaming_example.py
agent/llm_providers/__init__.py
agent/llm_providers/anthropic.py
agent/llm_providers/base.py
agent/llm_providers/model.py
agent/llm_providers/ollama.py
agent/llm_providers/openai.py
agentup-0.7.5.dist-info/METADATA
agentup-0.7.5.dist-info/WHEEL
agentup-0.7.5.dist-info/entry_points.txt
agentup-0.7.5.dist-info/licenses/LICENSE
agentup-0.7.5.dist-info/RECORD
