Metadata-Version: 2.4
Name: agentup
Version: 0.7.5
Summary: Create AI agents with all the trappings, out of the box.
Author-email: Luke Hinds <luke@rdrocket.com>
License-File: LICENSE
Requires-Python: >=3.11
Requires-Dist: a2a-sdk[sql]>=0.3.0
Requires-Dist: aiohttp>=3.12.15
Requires-Dist: asgi-correlation-id>=4.3.4
Requires-Dist: asyncio>=3.4.3
Requires-Dist: authlib>=1.6.0
Requires-Dist: click>=8.1.0
Requires-Dist: fastapi[standard]>=0.115.12
Requires-Dist: fastmcp>=2.8.1
Requires-Dist: httpx>=0.28.1
Requires-Dist: importlib-metadata>=8.7.0
Requires-Dist: jinja2>=3.1.0
Requires-Dist: mcp>=1.0.0
Requires-Dist: numpy>=1.26.4
Requires-Dist: packaging>=23.0
Requires-Dist: pillow>=11.3.0
Requires-Dist: psutil>=7.0.0
Requires-Dist: pydantic-settings>=2.7.0
Requires-Dist: pydantic>=2.11.5
Requires-Dist: pyjwt>=2.10.1
Requires-Dist: pytest-asyncio>=1.0.0
Requires-Dist: pytest>=8.4.0
Requires-Dist: python-dotenv>=1.1.0
Requires-Dist: pyyaml>=6.0.1
Requires-Dist: questionary>=2.0.1
Requires-Dist: redis>=6.2.0
Requires-Dist: semver>=3.0.4
Requires-Dist: structlog<26.0.0,>=25.4.0
Requires-Dist: uvicorn>=0.34.3
Requires-Dist: valkey>=6.0.0
Provides-Extra: agent
Requires-Dist: pytest-asyncio>=0.23.0; extra == 'agent'
Requires-Dist: pytest>=8.0.0; extra == 'agent'
Provides-Extra: crewai
Requires-Dist: crewai>=0.157.0; extra == 'crewai'
Provides-Extra: dev
Requires-Dist: bandit[toml]>=1.8.0; extra == 'dev'
Requires-Dist: mypy>=1.13.0; extra == 'dev'
Requires-Dist: pre-commit>=4.2.0; extra == 'dev'
Requires-Dist: pytest-cov>=6.0.0; extra == 'dev'
Requires-Dist: pytest-watch>=4.2.0; extra == 'dev'
Requires-Dist: ruff>=0.8.0; extra == 'dev'
Requires-Dist: twine>=6.0.0; extra == 'dev'
Requires-Dist: types-pyyaml>=6.0.0; extra == 'dev'
Requires-Dist: types-requests>=2.32.0; extra == 'dev'
Provides-Extra: docs
Requires-Dist: mkdocs-git-committers-plugin>=0.2.3; extra == 'docs'
Requires-Dist: mkdocs-git-revision-date-localized-plugin>=1.4.7; extra == 'docs'
Requires-Dist: mkdocs-glightbox>=0.4.0; extra == 'docs'
Requires-Dist: mkdocs-include-markdown-plugin>=6.2.5; extra == 'docs'
Requires-Dist: mkdocs-material>=9.6.16; extra == 'docs'
Requires-Dist: mkdocs-mermaid2-plugin>=1.1.1; extra == 'docs'
Requires-Dist: mkdocs-minify-plugin>=0.8.0; extra == 'docs'
Requires-Dist: mkdocs>=1.6.1; extra == 'docs'
Requires-Dist: pymdown-extensions>=10.12.1; extra == 'docs'
